mcp_git/__init__.py
mcp_git/__main__.py
mcp_git-0.2.0.dist-info/METADATA
mcp_git-0.2.0.dist-info/WHEEL
mcp_git-0.2.0.dist-info/entry_points.txt
mcp_git-0.2.0.dist-info/licenses/LICENSE
mcp_git-0.2.0.dist-info/RECORD
