Metadata-Version: 2.3
Name: mcp-git
Version: 0.2.0
Summary: A Model Context Protocol server providing tools to read, search, and manipulate Git repositories programmatically via LLMs
Author: Anthropic, PBC.
Maintainer-email: David Soria Parra <davidsp@anthropic.com>
License: MIT
Keywords: automation,git,llm,mcp
Classifier: Development Status :: 4 - Beta
Classifier: Intended Audience :: Developers
Classifier: License :: OSI Approved :: MIT License
Classifier: Programming Language :: Python :: 3
Classifier: Programming Language :: Python :: 3.10
Requires-Python: >=3.10
Requires-Dist: click>=8.1.7
Requires-Dist: gitpython>=3.1.43
Requires-Dist: mcp>=0.6.0
Requires-Dist: pydantic>=2.0.0
